more.emit-0.2-py3.7-nspkg.pth
more/emit/__init__.py
more/emit/app.py
more/emit/tests/test_emit.py
more.emit-0.2.dist-info/LICENSE.txt
more.emit-0.2.dist-info/METADATA
more.emit-0.2.dist-info/WHEEL
more.emit-0.2.dist-info/namespace_packages.txt
more.emit-0.2.dist-info/top_level.txt
more.emit-0.2.dist-info/RECORD
